candleplot_trade/__init__.py
candleplot_trade/candles.py
candleplot_trade/decisions.py
candleplot_trade/errors.py
candleplot_trade/example_trade.py
candleplot_trade/figures.py
candleplot_trade/helpfuncs.py
candleplot_trade/indicators.py
candleplot_trade/params.py
candleplot_trade/plot.py
candleplot_trade/setup.py
candleplot_trade/simple_trade.py
candleplot_trade/trade.py
candleplot_trade-0.16.dist-info/METADATA
candleplot_trade-0.16.dist-info/WHEEL
candleplot_trade-0.16.dist-info/top_level.txt
candleplot_trade-0.16.dist-info/RECORD
