Metadata-Version: 2.1
Name: candleplot-trade
Version: 0.16
Summary: online trading based on indicators and candles
Home-page: UNKNOWN
Author-email: info@zungl.ru
License: UNKNOWN
Platform: UNKNOWN
Requires-Dist: pandas (==1.1.2)
Requires-Dist: numpy (==1.19.1)
Requires-Dist: yfinance (==0.1.59)
Requires-Dist: matplotlib (==3.3.1)
Requires-Dist: plotly (==4.13.0)
Requires-Dist: IPython (==7.18.1)
